QuantTraderLib/__init__.py
QuantTraderLib/backtest/__init__.py
QuantTraderLib/backtest/event_base.py
QuantTraderLib/backtest/pnl.py
QuantTraderLib/backtest/vectorized.py
QuantTraderLib/backtest_source/__init__.py
QuantTraderLib/backtest_source/_plotting.py
QuantTraderLib/backtest_source/_stats.py
QuantTraderLib/backtest_source/_util.py
QuantTraderLib/backtest_source/autoscale_cb.js
QuantTraderLib/backtest_source/lib.py
QuantTraderLib/backtest_source/source.py
QuantTraderLib/data/__init__.py
QuantTraderLib/data/clean_data.py
QuantTraderLib/data/get_data.py
QuantTraderLib/plot/__init__.py
QuantTraderLib/plot/plot.py
QuantTraderLib/plot/ultils.py
tests/__init__.py
tests/backtest_test.py
tests/cleandata_test.py
tests/getdata_test.py
QuantTraderLib-1.0.23.dist-info/LICENSE
QuantTraderLib-1.0.23.dist-info/METADATA
QuantTraderLib-1.0.23.dist-info/WHEEL
QuantTraderLib-1.0.23.dist-info/top_level.txt
QuantTraderLib-1.0.23.dist-info/RECORD
